urtypes/__init__.py
urtypes/bytes.py
urtypes/cbor/COPYING
urtypes/cbor/__init__.py
urtypes/cbor/data.py
urtypes/cbor/decoder.py
urtypes/cbor/encoder.py
urtypes/crypto/__init__.py
urtypes/crypto/account.py
urtypes/crypto/bip39.py
urtypes/crypto/coin_info.py
urtypes/crypto/ec_key.py
urtypes/crypto/hd_key.py
urtypes/crypto/keypath.py
urtypes/crypto/multi_key.py
urtypes/crypto/output.py
urtypes/crypto/psbt.py
urtypes/registry.py
urtypes-1.0.0.dist-info/LICENSE.md
urtypes-1.0.0.dist-info/METADATA
urtypes-1.0.0.dist-info/WHEEL
urtypes-1.0.0.dist-info/RECORD
