Metadata-Version: 2.1
Name: urtypes
Version: 1.0.0
Summary: Python implementation of the Blockchain Commons UR Types specification
License: MIT
Author: Jeff S
Author-email: jeffreesun@protonmail.com
Requires-Python: >=3.12.3,<4.0.0
Classifier: License :: OSI Approved :: MIT License
Classifier: Operating System :: OS Independent
Classifier: Programming Language :: Python :: 3
Project-URL: Bug Tracker, https://github.com/selfcustody/urtypes/issues
Project-URL: repository, https://github.com/selfcustody/urtypes
